tfview/__init__.py
tfview-0.1.0.dist-info/METADATA
tfview-0.1.0.dist-info/WHEEL
tfview-0.1.0.dist-info/RECORD
