Metadata-Version: 2.3
Name: tfview
Version: 0.1.0
Summary: Coming eventually
Author-email: Dave Pearson <davep@davep.org>
Requires-Python: >=3.8
